{
  "creds": {
    "noiseKey": {
      "private": {
        "type": "Buffer",
        "data": "AA+nVDZSNsY0LjpNdprJpFVRqkIbMqKh/EPtxFl4eVU="
      },
      "public": {
        "type": "Buffer",
        "data": "J58MZ/aOBkNYRc+PpDAutKyhQd0R2t3P7HUNRtIcdSA="
      }
    },
    "signedIdentityKey": {
      "private": {
        "type": "Buffer",
        "data": "2GRcjzOEU9Ct9gORgQrqAEL6QK8n0E6qhiNKSB1NoGk="
      },
      "public": {
        "type": "Buffer",
        "data": "4eCRht1fwybyxoqPxCVuioBfiYh9ksIuW2iMxTFh+FM="
      }
    },
    "signedPreKey": {
      "keyPair": {
        "private": {
          "type": "Buffer",
          "data": "gCJoOKJX1bSrg0Np1TMZXB6UcIVWynb8W1A6mxOe5Hg="
        },
        "public": {
          "type": "Buffer",
          "data": "lC1qLT/XOAlRWExxZZ+ob7/Etm400M3ZnHCLbfMIOl0="
        }
      },
      "signature": {
        "type": "Buffer",
        "data": "QG/0L61IjPNg2e0yTAiJE6YlPG4X/sGTV0MCcp5PWdm6ARFg0U2AjVnmZslWO1ijVf+5Wrw7ads4jgpiTrj/Bw=="
      },
      "keyId": 1
    },
    "registrationId": 13,
    "advSecretKey": "sxFKtI2R1GVpcWYmNDpfqJiupHXoRS46QbKWHCrXjkc=",
    "processedHistoryMessages": [
      {
        "key": {
          "remoteJid": "917576026856@s.whatsapp.net",
          "fromMe": true,
          "id": "8D8D00168B3093EC8CCFD47D960612A4"
        },
        "messageTimestamp": 1665286187
      },
      {
        "key": {
          "remoteJid": "917576026856@s.whatsapp.net",
          "fromMe": true,
          "id": "2E13B9118882604B3E2DD33D4CAD084D"
        },
        "messageTimestamp": 1665286187
      },
      {
        "key": {
          "remoteJid": "917576026856@s.whatsapp.net",
          "fromMe": true,
          "id": "65F052ECD48DBE9E636F0A5705232CCF"
        },
        "messageTimestamp": 1665286189
      }
    ],
    "nextPreKeyId": 31,
    "firstUnuploadedPreKeyId": 31,
    "accountSettings": {
      "unarchiveChats": false
    },
    "account": {
      "details": "CJ7yv8YHEKaAiZoGGAE=",
      "accountSignatureKey": "Z8Z8NNk53pjSvJK0481XtU4b5Fiw9sMrI7zfVBIZ5w4=",
      "accountSignature": "aU6PLTIXsCLAbXecYFaSolIo2fW9bUZJgYd1mLIOvBdAW0DrcguQ/3I6/sq4EBUVjhsAmCHDpujNEB9gvJYaDw==",
      "deviceSignature": "fGKqcGkpAE5OHbcjCNthMNlPNu07uswoR9w+kOmV2tYEgVOXgyHx5f9HAL60QB8crX9rhG6B7geAMCwqvl2BBw=="
    },
    "me": {
      "id": "917576026856:4@s.whatsapp.net",
      "name": "Nvm"
    },
    "signalIdentities": [
      {
        "identifier": {
          "name": "917576026856:4@s.whatsapp.net",
          "deviceId": 0
        },
        "identifierKey": {
          "type": "Buffer",
          "data": "BWfGfDTZOd6Y0ryStOPNV7VOG+RYsPbDKyO831QSGecO"
        }
      }
    ],
    "platform": "android",
    "lastAccountSyncTimestamp": 1665286185,
    "myAppStateKeyId": "AAAAAF3j"
  },
  "keys": {
    "preKeys": {
      "1": {
        "private": {
          "type": "Buffer",
          "data": "GJNURk4Bj42pj1/TDqvILgdn1ta+myGWbQdtTFmwjk4="
        },
        "public": {
          "type": "Buffer",
          "data": "CNgDZEsmPPQsKF5Gk0PsxSOLZ0W/mwecZ1LVXSLRYCI="
        }
      },
      "2": {
        "private": {
          "type": "Buffer",
          "data": "cFSpALdcRIdgjdvT4OttHL/ok4A5iEe+EbCvT6iKXWY="
        },
        "public": {
          "type": "Buffer",
          "data": "eBeFbK9uzswXJ3p8nxppYcN0bMHV9rUjaVtBPZEV1y8="
        }
      },
      "3": {
        "private": {
          "type": "Buffer",
          "data": "eBOUduK01JoLoYSPax2mbfX2is424D2AACRKRp9lV1E="
        },
        "public": {
          "type": "Buffer",
          "data": "HC2iFKuC9TTKIZYSmJdDom+wfiMzPUuen5Y4APYEABo="
        }
      },
      "4": {
        "private": {
          "type": "Buffer",
          "data": "mKnuzlTRSYD0hQRv1ctUHKHsVe+6kK6XbkaeQFY0xE8="
        },
        "public": {
          "type": "Buffer",
          "data": "SJAqz2VtE97xl4tzcwg24DjTDBQQaemHEfmL3ovpDBs="
        }
      },
      "5": {
        "private": {
          "type": "Buffer",
          "data": "8M4DhhuyGSJZ9x2oNOfzJX5KMoXKti/dCSQIpi5luWE="
        },
        "public": {
          "type": "Buffer",
          "data": "xm98pOKXXsqaxejrp3WeMpmOkiXq0ZJjHA2ud9i9F0s="
        }
      },
      "6": {
        "private": {
          "type": "Buffer",
          "data": "qKhNQFfr6hE7rKOILlm3ve3kbE7aXGJlTd1oticJxFo="
        },
        "public": {
          "type": "Buffer",
          "data": "HuACorJkkzssRR7pJvqgO/sve1C3HuUG6aomFRIghVY="
        }
      },
      "7": {
        "private": {
          "type": "Buffer",
          "data": "cB1WxGbNP586rMUrS55+w/bzwDXU3d6xVxqluu1uxWk="
        },
        "public": {
          "type": "Buffer",
          "data": "pTTShArO/lTSAeNAUBEB27OzbuZdZ8BY94GwO4G1xgA="
        }
      },
      "8": {
        "private": {
          "type": "Buffer",
          "data": "kBzjz3yb00GU2gIq2gdNfkIh5iDjB4d802l6SyIqvWI="
        },
        "public": {
          "type": "Buffer",
          "data": "MyzjSNTcIJfbc6kt5f/U7jhW8vmzqS1mOumwAIbEFzE="
        }
      },
      "9": null,
      "10": {
        "private": {
          "type": "Buffer",
          "data": "sLvOBlGym6B8QdYY3/pAw3oQsGUrwEchVSG5gbg2VVM="
        },
        "public": {
          "type": "Buffer",
          "data": "U7cWuDdBe8wRktxF6iKfQtsedbuT6SbCKTfzgO9vXDA="
        }
      },
      "11": {
        "private": {
          "type": "Buffer",
          "data": "GN9AOqQ8UmqYNPNVyaIkAgP03zgfgPAXubU1qsJD+GA="
        },
        "public": {
          "type": "Buffer",
          "data": "sl3WlvEkKPpPWrH7whtDJC2M+xdTPJAWqS10umfYSF8="
        }
      },
      "12": {
        "private": {
          "type": "Buffer",
          "data": "0Aco4S8llpDYFkBDjg2zJKGZh9k2oW9aaGTtepzjfkU="
        },
        "public": {
          "type": "Buffer",
          "data": "CG0+y0cZWE14jhbFdAGxB6zP73IY15Wgu8F1+H7mCgg="
        }
      },
      "13": {
        "private": {
          "type": "Buffer",
          "data": "KIxiBPta93Q+LN+lUI07NRDa3J2st6TOcbHEXohX33c="
        },
        "public": {
          "type": "Buffer",
          "data": "cKqyZhhoDlyOVzLfFBjwnmQK2303Eu4ZLmOhOOD7cSA="
        }
      },
      "14": {
        "private": {
          "type": "Buffer",
          "data": "CDZIQzYlcFB2B5ySQVR0z+TBGsQN2auGS2dcPGYGXGs="
        },
        "public": {
          "type": "Buffer",
          "data": "U61rmpFPapYgmUrQNm/iZuM2jppr0Nk2/CtWNFYHZks="
        }
      },
      "15": {
        "private": {
          "type": "Buffer",
          "data": "WGxD7V+8SYg9DCKY89iFuf/uHp+FUCiyFtubEBVzFVA="
        },
        "public": {
          "type": "Buffer",
          "data": "GPzYevI2YMNH1/vyS3oAfsXsUwj9QS49KR8eiclz8Xo="
        }
      },
      "16": {
        "private": {
          "type": "Buffer",
          "data": "qDns7YbanAWDxUn5onWEE+ulDC5LHk9fzX/Ba1k1cEU="
        },
        "public": {
          "type": "Buffer",
          "data": "ERQ5fjzzSwSN6dtbROwOilvLyAI4Nk0JmICMEFnOgxc="
        }
      },
      "17": {
        "private": {
          "type": "Buffer",
          "data": "WGSfbatYHBfUBYA0DZhDkqB4NXEgBC9bdQDpe3d2xXA="
        },
        "public": {
          "type": "Buffer",
          "data": "8BClcEdXwHQyMGmq4czDU2dWxZPKnB6RRJ8SIP32VQc="
        }
      },
      "18": {
        "private": {
          "type": "Buffer",
          "data": "iABAbWKoEWrqmZlpNRhOZ/+jXo2K/nCqyQ/Mu6lc+kU="
        },
        "public": {
          "type": "Buffer",
          "data": "uQ+LhDhueydbNJo+Zpoz9RQrwUMptZ2iZrTKYNXeKg4="
        }
      },
      "19": {
        "private": {
          "type": "Buffer",
          "data": "8PFUwPs77t+is/fiqEWiao5CjJ98khlpuQbXNhwTxXA="
        },
        "public": {
          "type": "Buffer",
          "data": "kIbTDAy9uv2ybKn7L9ScJfEQflU75P2HDULMkFsNiUk="
        }
      },
      "20": {
        "private": {
          "type": "Buffer",
          "data": "SDKhOFjFpFL1ijyEWZGj5MfrCRiXO8pDhhPY8mFsf3g="
        },
        "public": {
          "type": "Buffer",
          "data": "jXa4sQdYlaCmDIxBxWCr9Ew+rYffrWYe03LGdLwqThs="
        }
      },
      "21": {
        "private": {
          "type": "Buffer",
          "data": "0KfxR9EbIY0eDvLMKFIEOhT5OM//kD41dFS0pidVgUg="
        },
        "public": {
          "type": "Buffer",
          "data": "+Ine7dRhKBj4ypvv3rRfmzMvdaeHTYrVbL080uygaDg="
        }
      },
      "22": {
        "private": {
          "type": "Buffer",
          "data": "wGKRVTFh69/g3i+5wuh0WlAeKoPJWqdjgqa+hdgQ4WM="
        },
        "public": {
          "type": "Buffer",
          "data": "VvOATacPUkVsnLKUO2q2f7Q41cmHhz3AFYhcBMovznI="
        }
      },
      "23": {
        "private": {
          "type": "Buffer",
          "data": "GLY5ZKmRvlBqzHPGn7Wnx01xtnjAd9CniQ/4VSvdPFE="
        },
        "public": {
          "type": "Buffer",
          "data": "J+oj+/y09Jb3aPhGwsE5QBuPQHAUCr5BKTp87fCTiE8="
        }
      },
      "24": {
        "private": {
          "type": "Buffer",
          "data": "IFoE/wRw6BdmZiR9d+qOvttPxy3jCN4xJ+sJa0CkQXk="
        },
        "public": {
          "type": "Buffer",
          "data": "YVCLkGW72U49TQ81XrVHz4X8vJ3ZaTPLvbc2+LXvUiQ="
        }
      },
      "25": {
        "private": {
          "type": "Buffer",
          "data": "wBOdtU9Mjnd68xoWHPHLwHYTOedORhV376owf1/B13M="
        },
        "public": {
          "type": "Buffer",
          "data": "s18prwM7f7SGM7bqgD7WvqnONL8sTTB3AbfRfRnk31Y="
        }
      },
      "26": {
        "private": {
          "type": "Buffer",
          "data": "eAVUMX5Saz4jLx1I8UsXJYk13ODVj+fAiLjLrHD+wEQ="
        },
        "public": {
          "type": "Buffer",
          "data": "aeTmJY8oEQdboeAbJ7fHuLgxRnqb8VdOvqY0b6buCHs="
        }
      },
      "27": {
        "private": {
          "type": "Buffer",
          "data": "SA2MRJcYTq86IOLXIPcWgwnuGOscYgyn8zR6bSS4okM="
        },
        "public": {
          "type": "Buffer",
          "data": "AupiF3DvM4ddI8XIwOHX5TmGEvf9Fder7OtplbEpa1I="
        }
      },
      "28": {
        "private": {
          "type": "Buffer",
          "data": "MDe9tJqNpaCe6p8rJYG+WhNUnmsKjWDar4sl7soaU0Y="
        },
        "public": {
          "type": "Buffer",
          "data": "K7aw32jfh/Q07qgs/7iAsLEhT5EAtRnNWNFkiipEBSw="
        }
      },
      "29": {
        "private": {
          "type": "Buffer",
          "data": "CDMvbgJTGMUS3PWces0T4cOZz52drQHjVYZz5Xw8Rmw="
        },
        "public": {
          "type": "Buffer",
          "data": "uBa1NEy0K7ZyRbAwMRa6r/uSMoHx+JTLpJg2nCkDkXY="
        }
      },
      "30": {
        "private": {
          "type": "Buffer",
          "data": "SKVOnXkcvVWs8BMqlDf/8mCjEkursUKFZpZemx/GKU4="
        },
        "public": {
          "type": "Buffer",
          "data": "kyhHPQiyVYSP4ykGSvsy/gj85AkcAOuDs4AFJdt9lQc="
        }
      }
    },
    "sessions": {
      "917576026856.0": {
        "_sessions": {
          "BTX2I6xwTznIrt7YHCeC5VekP0HTtqaQKvSKc0cNzyo0": {
            "registrationId": 1539468316,
            "currentRatchet": {
              "ephemeralKeyPair": {
                "pubKey": "BdqxVKERCdIJFoSxiUByhuvRhGZ7uFFyjvIpVFBieNdh",
                "privKey": "aKdStex6afYgsob/xypLc+YsLICAgHcZdYzkRkzg5GM="
              },
              "lastRemoteEphemeralKey": "BVgba7ZVj0tFlTRimc7alHZFZb9yPu4/qnXx/YTe1Whg",
              "previousCounter": 0,
              "rootKey": "beNnOCsFVSMUx2LU8oqRl9RMJV40eDpXWFAx2aBDNHE="
            },
            "indexInfo": {
              "baseKey": "BTX2I6xwTznIrt7YHCeC5VekP0HTtqaQKvSKc0cNzyo0",
              "baseKeyType": 2,
              "closed": -1,
              "used": 1665286186831,
              "created": 1665286186831,
              "remoteIdentityKey": "BWfGfDTZOd6Y0ryStOPNV7VOG+RYsPbDKyO831QSGecO"
            },
            "_chains": {
              "BVgba7ZVj0tFlTRimc7alHZFZb9yPu4/qnXx/YTe1Whg": {
                "chainKey": {
                  "counter": 6,
                  "key": "iaaV0FK5t7wf9hOozf9rkJb6zmlb4ri9Cc9iYwIhTys="
                },
                "chainType": 2,
                "messageKeys": {}
              },
              "BdqxVKERCdIJFoSxiUByhuvRhGZ7uFFyjvIpVFBieNdh": {
                "chainKey": {
                  "counter": 1,
                  "key": "QlGo8BtVapEN36WiayBSmp4RXDop79U/oMeZQHr/BZM="
                },
                "chainType": 1,
                "messageKeys": {}
              }
            }
          }
        },
        "version": "v1"
      }
    },
    "appStateSyncKeys": {
      "AAAAAF3j": {
        "keyData": "QAHzQO2oIC+5fW/EtXFo2BWKdQggLXhg+0tP2XJnVrw=",
        "fingerprint": {
          "rawId": 2026895646,
          "currentIndex": 1,
          "deviceIndexes": [
            0,
            1
          ]
        },
        "timestamp": "1665286186278"
      }
    },
    "appStateVersions": {
      "critical_block": {
        "version": 1,
        "hash": {
          "type": "Buffer",
          "data": "U0PRD5UyzKSO1Qqudqj6/0+1tX1rkbUJIi+9tdYhrpozRMGanbFs+NNJGAgnAPv4e3XXiho3tMmstsNUyyNBGReyzr0Ac6jwq2SfWsXC5Wvkhtz9UQgem1UMBDO7A6wQ1PTdwVS23DycmPPh34kiOo6LMSqWUE34JcZtgpahGjw="
        },
        "indexValueMap": {
          "FSJhubB8kJumc6jSqa5r5cotlGotG1Wf6HJYUgJg5Zc=": {
            "valueMac": {
              "type": "Buffer",
              "data": "00imMXax7VJmmobWTFsiR/bDTd8dV7H4ex1jzkA4hmM="
            }
          },
          "1Xsx+vqFTIDHHkycX2wNc7uSOvRUQfrO37fSDbqE1y0=": {
            "valueMac": {
              "type": "Buffer",
              "data": "EIoNr67jGt3A0jS4umGyAwb+Yloxcg1iLw62ha1A/k4="
            }
          }
        }
      },
      "regular": {
        "version": 1,
        "hash": {
          "type": "Buffer",
          "data": "BbOlH5JXDJ6fYm4brKbJqAZJikx7tiurK4U8z3QF2ubz8PcvKocb3D8Anaq6K8Q0b7yCtKMN9eJNUtgeESZRVz0k4Q6Z3jVUd4oBKBfURbDocqAaS5gD2P+ttARRL7Z0EdWMqWJFD0B0+JQDe72xfdzgYL6bWWdfEsSyZ7xf7f0="
        },
        "indexValueMap": {
          "I9+kXIWQZcPPZrTSwRNDDdP+M3QWZN0T7dYPhfmQSpA=": {
            "valueMac": {
              "type": "Buffer",
              "data": "jGbaiER2tr55GOxrvV4fVsa6idGdRn3VDtuBgaEatTs="
            }
          }
        }
      },
      "critical_unblock_low": {
        "version": 1,
        "hash": {
          "type": "Buffer",
          "data": "3DlTOIBJwLSTTE00K6rj1QGS1MMyD6woRPZPrbDMwEJ1hgCfj/l2ZeHZwpyxk4IhPqRLvIOBhROmzp44D0g1M6zSxuOtXK8rnC4iSdMLB8ZZrMoSLrfFk9kWt7tZNssejQCK/FpZ7qbWS87y5/CZc7LpQSvI5/Lm68fzE8qwaMM="
        },
        "indexValueMap": {
          "Cdk604DF8+S1Rxq7YCuRQPm8YDlSubO8B8oN0EVZQwE=": {
            "valueMac": {
              "type": "Buffer",
              "data": "tQe3LYUtqGoMrA0cD7lPIUDmR47lmVjRYMkEuDuply4="
            }
          },
          "QCOd3TzsRFkcBX2jIDeVV718WA6b9ezwf+AZogBDtHs=": {
            "valueMac": {
              "type": "Buffer",
              "data": "jaseZ/ATPj5BFCFAV4IW+XT8zrrJTiJn9itnt9QC4mg="
            }
          },
          "6g+SaqMzz/0cEMovBW8Kz0dXvYoMqycz3RlilxjVZmM=": {
            "valueMac": {
              "type": "Buffer",
              "data": "/vLljNRLf+xF5Qs5MIz/j6n0xK9LrYdAwiLrGPH/KaU="
            }
          },
          "Yl0vmgHMqOPllDJ3O+A2hxsHskhZLhSiOJOZtwUkBHw=": {
            "valueMac": {
              "type": "Buffer",
              "data": "KDFwopPTskBLkN+Kkn4IIuU5WucSMMLIjpUvXaDIL70="
            }
          },
          "wdfuDWAvhyUfYlE3q3jY5mvy3yFdrRMWwHOX2zrV2YI=": {
            "valueMac": {
              "type": "Buffer",
              "data": "JUnjKQ5slv9zyohk2I1JeJt9GO2NMPQluRtc0VZftlY="
            }
          },
          "oMxJRjgGzXNEoC81ESWFcQA+cvFYk+KK4SGOFw/qMpI=": {
            "valueMac": {
              "type": "Buffer",
              "data": "SpQcKy5ZJBszB2SkNFOVLzfy3+y3wDQ7zKYnBuedpSY="
            }
          },
          "wcgsUxhZVAoQBbCXbE3Gg2jhIAmQ5H4wc4h/w7v0VR0=": {
            "valueMac": {
              "type": "Buffer",
              "data": "LLE2+zOm39ZVaYhcV71Fe1N6fmFmS205W6r8Ly95nt4="
            }
          },
          "nZxupohmEguzysAS02olAWobzNrg6Lsi6KiqM1fO+N0=": {
            "valueMac": {
              "type": "Buffer",
              "data": "jpvZ7v+VFICe4qrSTZzf1HYwuOP/P5ErsEt0BuyOfH0="
            }
          },
          "KzL2Jt5GuTr0nT3ZkkJAS46ATAA38oMGrnTUfQa+8uI=": {
            "valueMac": {
              "type": "Buffer",
              "data": "XuP8srFux4RTY3k8HWXb5I839X9XZdw3Fk6+EHhL7Mo="
            }
          },
          "ya4D0CVx3fhFAmXd21EFCJWhzkIM6qKxt8WnGMjpjdE=": {
            "valueMac": {
              "type": "Buffer",
              "data": "56Imo/YTL4D6hEmr7sL1sbcDlzBHZFiJJ9tm3hPnhRg="
            }
          },
          "ztJr1qa4cPAFU0J4W3LXfKHjW4NNXd4RGSz/W41tZT0=": {
            "valueMac": {
              "type": "Buffer",
              "data": "o2UUY8VXMWIHQHS92OjvdmhIllpiUhwqdsygFaMrx68="
            }
          },
          "gFAGLBFCprtYENMUgfxs4gWNSOs5s11PURMRl8nYP8o=": {
            "valueMac": {
              "type": "Buffer",
              "data": "Hjy0SFn/Vt+RFj8vskDeXNI7OnruJcrzT7y74fU2dNU="
            }
          },
          "HFpbeO42N0HxHpCqRJiT1rKNzEM/gYwhPNKquAxaEgg=": {
            "valueMac": {
              "type": "Buffer",
              "data": "V+cKQmCjxh0fLi7r668lu7JigppfEt6pELfZWY9Ja0Y="
            }
          },
          "0717EMKWMnH5mGjZn+wk9vIdcIleAV6Ncsg7vfnay5w=": {
            "valueMac": {
              "type": "Buffer",
              "data": "DZinUOKuIby+em2P+uY9ZHm2brGGoTLo9IB7qeeEYoo="
            }
          },
          "cqdlXRsmdmKzxT805WNSv7hzMt4At43VA+xTu2x5Zho=": {
            "valueMac": {
              "type": "Buffer",
              "data": "khtC4y/ZOQ0RXTkxfqJVeU5DxMGtCnI1FhD7tskhDcU="
            }
          },
          "CzpSpkVtBDUMz7rH+UFVvp6dazxyEATw7Wn8S9+yj3g=": {
            "valueMac": {
              "type": "Buffer",
              "data": "hWsxFHbucqW2ER17lSP5f15yciSoLOiwjqdyhsctEWw="
            }
          },
          "H7UPnF7bUKdm5fShpCMtV+fKZ/4zQjC/x+POT3HnQNw=": {
            "valueMac": {
              "type": "Buffer",
              "data": "6jqNhrHBf32VVD9B7gdYC6/+LcvYzCEmwEFXRC6KLf4="
            }
          },
          "K9XA9MFydPVmFLJy6fAtteu4rc0S/9r29qY3e2iDics=": {
            "valueMac": {
              "type": "Buffer",
              "data": "how0wI80Qp+5jYffX+gcSVNcM9HudoSSxSS7SVkEqgU="
            }
          },
          "FxSjcnbx3jOF+UGm6RD0Xh6KOfLjFDN+KE9eyn0IIBo=": {
            "valueMac": {
              "type": "Buffer",
              "data": "TkNZFAZwnF5htyAuNFjJqqwaTmO1Wfrm+UHUGUxGdU0="
            }
          },
          "VoAyKHr4uzwPy2GDZCwXt19W7G4oY+2ely2uX1D9r8E=": {
            "valueMac": {
              "type": "Buffer",
              "data": "DPQyxzy30AgXaYHSExTi69gciUND72m0DLgJrnXKHQY="
            }
          },
          "Qq4tDHhO64WCM82KbbryZL7OiHFrdUIkgN0GKtad83M=": {
            "valueMac": {
              "type": "Buffer",
              "data": "59Ivq/WZidH9j25KZwuEWi7jdYyHI6qHf8SSaw7LkVA="
            }
          },
          "kafYPMItlH1ox4p6aeiLWl6nBstburlIfhp+gcPKy2c=": {
            "valueMac": {
              "type": "Buffer",
              "data": "K6YLyAOR/o+VUIjYcUzSe2wWT0e/uBYj9zxvY9NDkec="
            }
          },
          "W232FHoLjCDaDCpQUX4qITGKW5aXr0N1RnktfvdEO9s=": {
            "valueMac": {
              "type": "Buffer",
              "data": "P2rGIdE0lgtsnl9yzRoIditFpvDn5ehFQl6bMmVYbCo="
            }
          },
          "oujr32FFXDINABSOOA759KfsypT63clC3rADPnNOV+g=": {
            "valueMac": {
              "type": "Buffer",
              "data": "8qMfE+N3YG0JVh3Wdw5HheQ9qPMDBMKYAdlKjpYDeFU="
            }
          },
          "K+W3MO64cu64ugjN/hWRJAworBrEmgNgqDjsAgbEWUg=": {
            "valueMac": {
              "type": "Buffer",
              "data": "4pXQr89FJnj36KJ074Hm1j19ASBD/xlWTGldzSmT28I="
            }
          },
          "oGM42Qw8wODICniKZFXBywKY1V2wJlHmNbi/Q2XcSHU=": {
            "valueMac": {
              "type": "Buffer",
              "data": "RSt1vYrslRuMtyTUqfil2N54sN4r5CDWlUf3vEtltmg="
            }
          },
          "D3hKrH5/tX6IwNUExFt0MY+Farag+bJWyLS/A/WvxlM=": {
            "valueMac": {
              "type": "Buffer",
              "data": "nMvDWq+TdyOr11fDpSiBLeMk89CjvQL9qyM2rWHKIYw="
            }
          },
          "tq3+6OksduooGha3F147dsl4pBsBN9mQLgbhp8tCxNY=": {
            "valueMac": {
              "type": "Buffer",
              "data": "T0sX+8XVgVwEb6s3aGWCISS/ZkT2+wAgQimutZMCp6A="
            }
          },
          "i+2zsNwNsZ39YHVd2wwh0RYOcHJKcCulNYI0d67s01U=": {
            "valueMac": {
              "type": "Buffer",
              "data": "uhiJ8WQPdBCH5lU6xuv8RHTFeqeNteDJT9RLBnBp13c="
            }
          },
          "SB+kSx1jOWVRr4C5Pzrh+Q57soc666duEY5OFDSZFCk=": {
            "valueMac": {
              "type": "Buffer",
              "data": "GlLTHhBzratt4oNBltqKgpXyK8R+mmtp1Tpf6L6nZkc="
            }
          },
          "rbQPBEl+3J9fYncvdbnNMTfOKDB1M9faoJjmAIMEzAw=": {
            "valueMac": {
              "type": "Buffer",
              "data": "pCQbXRNuyG9JmfP4qQi0B5neHPNziAi1FRYGoW6k77M="
            }
          },
          "2JEjhLrila/4fvctM8JRjuWooQp/f7LCHYcRtKFSAu8=": {
            "valueMac": {
              "type": "Buffer",
              "data": "tSDf1+DuVLnc3Ye4cPRr7JU+0mRrt0EgZBZBtUiW/fw="
            }
          },
          "DfATs34WfsHFXYGBsTIe/51ijTfkKKphGC4yJ60U3Zo=": {
            "valueMac": {
              "type": "Buffer",
              "data": "Xb/t3hXatRKvzyIYXZBHyzccBNFaXrYsCZz99s7wFko="
            }
          },
          "QxWVfjjQbeyrIQP/Y0zaRT+57+iJnUroeQdTK8vFokc=": {
            "valueMac": {
              "type": "Buffer",
              "data": "Ej0bZSzT8DtidsackfocOC6L9GnRIRGxfE8sXAR+Eus="
            }
          },
          "HqQNSQrEKFH35bGq8JgzKP+06f1kKwD4hineRmVSmoM=": {
            "valueMac": {
              "type": "Buffer",
              "data": "gX+C0gnZ67BVgknTe0Rnq03XfZT2S3qrooE1j0OXWvY="
            }
          },
          "RvG+Mz76TCfS0m6typzxGh8dN6ZRQM/4BsnlzPLjjis=": {
            "valueMac": {
              "type": "Buffer",
              "data": "LNtGfrJUieq04Xox8cVUf1UCiwcjb6Ni0q9YawDnJ8M="
            }
          },
          "YP0f/vFPEwWtatkMaTO7YO1YJoQBnXgrlHFrHXLunqk=": {
            "valueMac": {
              "type": "Buffer",
              "data": "299eG8di9Hv1qeXftGd1RmB3WlkMGcUXYo6n1HJ/HjA="
            }
          },
          "gwE9XlXjXhoTWfxhhKViN42s2/r1cAV3b6TQbEQKPGg=": {
            "valueMac": {
              "type": "Buffer",
              "data": "cXy9gOfWlusPmv0VQ6lVThXGPQ9YJAqy3B8AfRs0shc="
            }
          },
          "UDmtSm8d54PLHxFoFoGScbeDbvgv7YpSnmRamq5g0Xs=": {
            "valueMac": {
              "type": "Buffer",
              "data": "qjRO2xrI8AfTtCVNYzqHxHhz2jpGdAH4hmZRCggWeJk="
            }
          },
          "rItyYGosbKI3rLWwg5l8eBYHYo3vXFDZTbUElxQBcBw=": {
            "valueMac": {
              "type": "Buffer",
              "data": "BDgxb6DLe5sRtHoVt/F4bgrEA+dxDivx0Jnn+fIGtpI="
            }
          },
          "FuHtGw3PhEXTnMFVTgm5rgGSEgUx3HJx+LJSsh6kobc=": {
            "valueMac": {
              "type": "Buffer",
              "data": "f/nPTijM3mCMjU2uG2ab07+S2hiz425X0TuPKl1o1HA="
            }
          },
          "ULGbSRm64/letbXcILCC4EtDc4njM0IEIrVzk74A0Qc=": {
            "valueMac": {
              "type": "Buffer",
              "data": "2BE9F7GeKFmjOMbsKcZiy5A0YZf1iwOEpbarIRaNa8s="
            }
          },
          "bPt51Td5XoJRnf6YVk92bdFV+0QbtbT9WBjFqvjfeww=": {
            "valueMac": {
              "type": "Buffer",
              "data": "zhL3QmQFfpKyLfo5ZW0aFFHH4LL+UBWNFzO/CGfKmfE="
            }
          },
          "ZiGU0y9+mtcl2xHS28R387YJKXt50vy/pFA8MQgabOQ=": {
            "valueMac": {
              "type": "Buffer",
              "data": "cxc0Ndbi9MYRURo662HbctnsWJUtm7/EpDQ1QuUlkeA="
            }
          },
          "gxMFzjVV6Z6tGkh2KAzyY6wnAUlj1DVGTWe2bMvclkI=": {
            "valueMac": {
              "type": "Buffer",
              "data": "91WYgGiFUZ3VzPeTHIpd/yCwTcZq11o7jQvQQaX47WI="
            }
          },
          "ZAFF+i1AinETPD4dwFwZasRcJGLPbfJmADIAMC7faoA=": {
            "valueMac": {
              "type": "Buffer",
              "data": "+7OPcXBPCu2oricj3YjcVOZNBNWIslXz8IH0tfsFkBA="
            }
          },
          "ClQobl1KNMWcakn/vfFeSwL5lWYKEHLoGIjD6poRE3k=": {
            "valueMac": {
              "type": "Buffer",
              "data": "DS5mRwJcnIStkVNA++GSQW/K8H2zHt9GvVm/dKgH2hk="
            }
          },
          "0Z5JtItAgQakf4XPl8nxKWmqpKDjrOqZMucZjT/cU4o=": {
            "valueMac": {
              "type": "Buffer",
              "data": "QZOOjTRjbUnlFZDRjLEUlWZO7F6VwOg4eGh7QeFNjtI="
            }
          },
          "EncYCgcVAxmjc1UI2vfKgyLrgMPpJz2eGMvv+/SMFOo=": {
            "valueMac": {
              "type": "Buffer",
              "data": "iG9BlCm9tP+IY5CiM9Mt3xBkYkyWw6Ick3zE94DwRqU="
            }
          },
          "ilV4wlDbERVryAXES8HM/nqGgZc/ZtBkuvOnQvWkgoY=": {
            "valueMac": {
              "type": "Buffer",
              "data": "zeVmXATZo5B1nBYO9GSJZiQtnooFDzH2BIv15/c7ROY="
            }
          },
          "5WJFc/mNh7RqX8otH8dJjbigPjKhVovsRzKwLaDqdJ8=": {
            "valueMac": {
              "type": "Buffer",
              "data": "4yIfU69E9jEQyL6fLF/44azZFNTwun6eqlC+GndVVbc="
            }
          },
          "u1WELUSFuHtxr7uDK6MWmK5wsnl5wSZyGisuqC+8zJo=": {
            "valueMac": {
              "type": "Buffer",
              "data": "HQ+BMkfmoN1hddBgX+8binOYfNxI6+6yUA3wynoVVHs="
            }
          },
          "zxBIX6S7bKLOiG7TPx/9/RuvCz8srT7scRMYDpwcSls=": {
            "valueMac": {
              "type": "Buffer",
              "data": "1CLLjl0omf5QG23pL/c/j93ZTMaoPjBVUnEFgGVT17E="
            }
          },
          "Dg8X2edwr7aAJ4X25h/OG/0hiQxGLmqRby12TJcMuwg=": {
            "valueMac": {
              "type": "Buffer",
              "data": "9ApnzYZk54ql52t/S8nsefc/uqqR+Cyv2OHk+BDAGKA="
            }
          },
          "iLm7Ma8FkI4vqeKKHwzqLrCdd+0nKmCA/DJ4P5LZWyI=": {
            "valueMac": {
              "type": "Buffer",
              "data": "s3ATN8Zqeyr5LKd7dRBiqGIaf5DkNKDkkCwLwqK7FSc="
            }
          },
          "bGeHFC4KXS2HK3EAR4bUUR8Z5+C+F+7SH9tLiAshg9Y=": {
            "valueMac": {
              "type": "Buffer",
              "data": "LX7FH64UUtq2JPLr7c6iaYrJu+nvwwxMyVTWWkPv6G0="
            }
          },
          "RF1gIYYdivvMvL8/0jn8iyV0OnjAD1rJz2npIU1z3co=": {
            "valueMac": {
              "type": "Buffer",
              "data": "Or6i3LeHzaw6figKKSCcpb11syxBkdMA6kjtxD52l+0="
            }
          },
          "90Lk4QFqtD+23U2Ehy/5YZfmdZnWjq3rLuMO4Kf16Dg=": {
            "valueMac": {
              "type": "Buffer",
              "data": "xz0JuFNtguA+IaPNQzEHW2PiAEwEyYAVvsKYt0nybBc="
            }
          },
          "EVLu+JTXVjzDBRZLqKR47Cqh8d6nKzHQZd75rB1kKWM=": {
            "valueMac": {
              "type": "Buffer",
              "data": "GHZAbwM14SB62fsuPxbvTwmhbUV4qb3ngzRzkGCNVGM="
            }
          },
          "DNN2LChADUyiH/D1KByqce1NIVFs5zjOYWVn8xEMxmY=": {
            "valueMac": {
              "type": "Buffer",
              "data": "JHRu+pmwxfKrbtCfP6RYw0Lj7lcIpvCYoJBPe2n3xio="
            }
          },
          "+gKn5wVEj/2yy4ZLKY3O5fsoiOUaFYW+WZWEbpaCTgM=": {
            "valueMac": {
              "type": "Buffer",
              "data": "2eD+zrf4gMbBHa9QN8EsHf8KNQlRXKHSVX8hWRrRRBo="
            }
          },
          "B2Sn9vGIqDNmHrjZ7tcDOrsRx5Xsrd73nNlmvNoCmWQ=": {
            "valueMac": {
              "type": "Buffer",
              "data": "d/5ylrGRZ+eMKWFoOmcZEkDvVhjYxXxo0b4Ly8fCuRk="
            }
          },
          "6WEoZ15VSl3xQi3o2aBVg884Wt7ozLzPHa0AkmaoCus=": {
            "valueMac": {
              "type": "Buffer",
              "data": "bc1HCr+xItkgjY39I6o0+F/2nlWOPeiWOSJDZhNU31k="
            }
          },
          "RVfh77nHizsVsMnqy4n5iREU+W+TD4RRkuAhgmy7mgU=": {
            "valueMac": {
              "type": "Buffer",
              "data": "iDAByJvLPRlQdMmC5n1YIlElYjSEMWYmZ50GMnbltlc="
            }
          },
          "4QpSip9nbRgNoC9ukJSH2VeZfb7rQKMTJuw54uDItYk=": {
            "valueMac": {
              "type": "Buffer",
              "data": "Kb74TUEKbz0z3yPK18efEscrRrHq9jHul7uvD1473Kw="
            }
          },
          "8T9v0dg2ORQmDEGZOBmEQsXrqyYsgc8uF/dtnutLLTA=": {
            "valueMac": {
              "type": "Buffer",
              "data": "KterxD8t6GLCHIlfbm1hfWvrGFS42D4G7zB+O06BQv0="
            }
          },
          "X92sk9clsD2oz1g7NlMFW9smhs1xINVi1aw4hIWlE5A=": {
            "valueMac": {
              "type": "Buffer",
              "data": "ih7JbHX3hXIqBKYHDEspbXbC24qUhWtCFauOgIh3niA="
            }
          },
          "DNlaKlH3dvTcFbd/acIFFDAHIjvvLvBSmH5Ca2emeAU=": {
            "valueMac": {
              "type": "Buffer",
              "data": "D8ankL8IDOdRrVC39j9I1Vu1dhoJjwCsSS6zt8hFTvk="
            }
          },
          "i39/c7X1hd51ffvmgsoA9ZKKpZ83doA6GNc1M+nbqn4=": {
            "valueMac": {
              "type": "Buffer",
              "data": "y6jVB4xxd2J4A9bOnTa/TWhcwsIPTrHSbiHxPubU87w="
            }
          },
          "/Lx/Mme8TjcZpj4EmkQqNUkJ1SX8l/xHCvUEj13rtrw=": {
            "valueMac": {
              "type": "Buffer",
              "data": "hmWw9xPupJ9pMyQU8lCtrvx4k+g/jLS8o99BJg7IEcg="
            }
          },
          "qz0XAxM4W2oGgsX4VROHXjXiQNGk5xMd9Fw7ytejJ28=": {
            "valueMac": {
              "type": "Buffer",
              "data": "peyKtycUpRrGgMKMsJ5XzsmAUiLyVzf77/l9zgkZSwQ="
            }
          },
          "Ky4y9iKuyGWD5q52P1Oc5o0JbysEjQbZ4UlbsicV3I0=": {
            "valueMac": {
              "type": "Buffer",
              "data": "p62GNPVesIb23Yo+tcEULstYAzP4FjcojAN/ZHv517c="
            }
          },
          "sjsJeI2shXdL4ZoMt6N5ALYrSuqwCuAQEO+A27lYrHI=": {
            "valueMac": {
              "type": "Buffer",
              "data": "Tw24yJQpZ6vQoPduzMh8TnwWkHAAs+VfE0OIdi8WC5U="
            }
          },
          "v22SGTIpJRcHfmInBHJEGBnrI5lJbQYu+cYJrwczxjQ=": {
            "valueMac": {
              "type": "Buffer",
              "data": "4cAwqcPHdEtzFI6yOQSwpd7uNDgxL/MSP7OKQs+Sjes="
            }
          },
          "4h32RNmpcBYz3QoNr9jUZRtjtA7Aeru0fN4zskwJj2k=": {
            "valueMac": {
              "type": "Buffer",
              "data": "XYzUc/23lwZQaTFGqBhDIqlG6YEkJ4Cm6nCqq0gNrZE="
            }
          },
          "lGYdNRevWJVgyGu+157z2v5T0G337ujZUugZY4/Tsnc=": {
            "valueMac": {
              "type": "Buffer",
              "data": "lcb0OnZmNX8nhd75njHE65lVMAeDa9RPaWBOlAJQrvc="
            }
          },
          "V7VQHAev1vgTg6R2IEU4iflctM3JCmArwygcpuEWcJw=": {
            "valueMac": {
              "type": "Buffer",
              "data": "9G4I1ka0U0YAvzoSs+4UWsdNuSh4P4eIyskyH2ss4CQ="
            }
          },
          "aMZZZc0nCDgZTcYXJp5zViKucTLnU1GD4rGOL105Ur8=": {
            "valueMac": {
              "type": "Buffer",
              "data": "DnUr9eVxGZ21GlUCIEj8gSNDj5R3zJKoW8zYMW7bRns="
            }
          },
          "rNXz2PQ83R5/V8Dn6SzasWBFBLZyyoqkmb5tmR0CR4E=": {
            "valueMac": {
              "type": "Buffer",
              "data": "azB0WTbL7Uv/H0dV3aHmV4brm4uJNGoyRpSoyTq16Ew="
            }
          },
          "CQS3yPp9E7FmYfyBstx+kVOi5lY8xlhzc6BgwIOZALw=": {
            "valueMac": {
              "type": "Buffer",
              "data": "s1wy1vyUCFdYPfDM/wUDqu/p/7FGO6dqEXXfj1vYfd0="
            }
          },
          "I9OUwnFDV8JFP2t55Lfc9HA6T+5CZ4lpXYQBu9Peohs=": {
            "valueMac": {
              "type": "Buffer",
              "data": "/AEifTKtP63AZf5rgdWtNAs86YhEvWx2/eXe0zV7ZMM="
            }
          },
          "yMBHVbU/mipHisi3BgqI8e++rHWWq42hFzyD5nhhQTk=": {
            "valueMac": {
              "type": "Buffer",
              "data": "iZVA/j8m9GchizkLApYH41VuowhPXJYcijU+X6apd5Y="
            }
          },
          "Egs/uLN5HOLw+PU85N0pJcxq6Y0RvEIR0RCusGHcnk0=": {
            "valueMac": {
              "type": "Buffer",
              "data": "PhTE1zEbx1vhniRB65/imiFz+lUjZrTiWWyqxpRxrl0="
            }
          },
          "MB7A4vUTLOPm+ueBxWJHfRKH6Va3iH4SzzqWqlcc2Aw=": {
            "valueMac": {
              "type": "Buffer",
              "data": "iGPeEqtK5C62Qp6lmpH2cEd5/FMOi/JO/QX2p7S6WV8="
            }
          },
          "CdLjNJCTDyKN3kvWAl0aa1BwZzu6MgjyTgYq/Q5jbvI=": {
            "valueMac": {
              "type": "Buffer",
              "data": "2KtOtpEJY6O6cxct4j0hbzpPVpdeRqJ6rsa3+Jf1mb0="
            }
          },
          "yh0zNXTF60ucZnaJJS8Pe4pRdCfaWpX8r6A/wCRDxsQ=": {
            "valueMac": {
              "type": "Buffer",
              "data": "241niJRjVxRx1eoAERC4IvwU/eNbpYzQFXOWWaYn8Sg="
            }
          },
          "5rBpD7DJNd71nYHGwIpcuLtrXyXGEMkK2OIqVJy1LYc=": {
            "valueMac": {
              "type": "Buffer",
              "data": "nS+FtYt6Q36tAZaLFZiMkC1JnsqAynYq3KYSd1Wb7no="
            }
          },
          "/8jkvR5FabEPQOHJH3APsRt/71ujrwmmuxRKiXvjwB8=": {
            "valueMac": {
              "type": "Buffer",
              "data": "V6AooRYO1AoclVw1k1rASx5WRFdMNWhlj3yaYkFmhd4="
            }
          },
          "yxKyB1PvTTisZog9GHKqDxVDXq6vGyqvtlq2gg1qBus=": {
            "valueMac": {
              "type": "Buffer",
              "data": "TUCQiPOQZ7MIbfb1rlgLhg0E+M1geJ2R4wuEzKnrEcg="
            }
          },
          "yA8crsvuad3uDyA75nd1yqg16A1XIFwgbEA735U92AQ=": {
            "valueMac": {
              "type": "Buffer",
              "data": "qVCrmtEqzfD6O9L1SJDwk7iy9V1SQTEXuwH1VprMI+A="
            }
          },
          "S/pKxMwzgevKrURKMoUkPT9RGVv7OV9xOKz3jlNY1cs=": {
            "valueMac": {
              "type": "Buffer",
              "data": "v/wGM2wFDNMmkZxUMA9P2FAuoLEb++GUb4R5PRP8bQ0="
            }
          },
          "3jjOCksRTFkls2GLFcxx6S0Q4/lTYxK2EciGqAmcyQg=": {
            "valueMac": {
              "type": "Buffer",
              "data": "JK9WrD5+ZISLlRh3yDBPMXidT/qiGhwxzPmCNG6+cKI="
            }
          },
          "3ve1XanKdohaQYg/eBUwyfDXpaQB7is5k0Q2f3G3+Io=": {
            "valueMac": {
              "type": "Buffer",
              "data": "xORMRxO01dC19kczqESfFs5oQXnZ5J7Z4Ffv3v3Ex00="
            }
          },
          "z0GKee7e/ORPleAPD1Xr/UoH5aXq1aLDx7/wUMS7ZMA=": {
            "valueMac": {
              "type": "Buffer",
              "data": "ESSnt//36Gsv4P00IeOnowwl9EqYC50VU022yYlr/hA="
            }
          },
          "QTlyhS5Gu8ptRzCXoj6jBmSh8tHjkq6zZ/Nx/kL2hUY=": {
            "valueMac": {
              "type": "Buffer",
              "data": "ZTIYnJ+rWtIfx0D4UCe64Lr0HZijTvKiGmk6n9YyRtU="
            }
          },
          "rh3FRqXO8zifJwHRERXSNE4U97PQnYcVN0feslSSIwY=": {
            "valueMac": {
              "type": "Buffer",
              "data": "p8iV/IDbplF3D5p1yY/D6ZZYdJXMtVv16lMRZNFEaek="
            }
          },
          "94kGqAnv88i3FbP0JvlwSPJv4SHj6i5ptwWUcehJKCI=": {
            "valueMac": {
              "type": "Buffer",
              "data": "/zPTz5h/fRY4L7l377kEtvlMkSkhiu5dBkBdlQz0E4U="
            }
          },
          "zn40VOORYDmaGH7wI5vPsCky4syWn4zoSuvSexD7RAc=": {
            "valueMac": {
              "type": "Buffer",
              "data": "OwyJ5HGtBcSrDTOLoDIMFti5+45xQg68utlspMb8O9g="
            }
          },
          "vgrjCv9ZJHbI95BChpA1p4Ypz5UkNSZpvJPTXoUiRtQ=": {
            "valueMac": {
              "type": "Buffer",
              "data": "qRflk4UmE8ilBp5ZKk53U604hljkEZJlAQCjNK5IRk0="
            }
          },
          "4T4WIT027T7buWCXVwZhAbCDKt/J1tGvsVMoGt7mWXk=": {
            "valueMac": {
              "type": "Buffer",
              "data": "ecu2QrosTvF+PXr+1KfPCya4B+lPFJ8vUhKOcolru8A="
            }
          },
          "4aEjWV7wOwoVpv2Xu8I9RF0hAxgJKPcFYjLFko4eEpU=": {
            "valueMac": {
              "type": "Buffer",
              "data": "oqrdBzmGW/E2hVw1jOze1WwWEyD89LF1dxUlEzuMZVs="
            }
          },
          "57TKR/rQ/XUDzT+8wsVci8UvpmtwLAunjFrB8/CFrIY=": {
            "valueMac": {
              "type": "Buffer",
              "data": "5k2fK2qDuQC72ukHwTSPAfxChycU9GRvzNLmNh0R5uE="
            }
          },
          "EepYfrph06QJJ+chB/TsAQjUkBJoPOZB1m3fA8XA4Ns=": {
            "valueMac": {
              "type": "Buffer",
              "data": "JeQTFSmDwGbJDZ14M8wZ4hXfUZVKH+jZgw/f8heVCrs="
            }
          },
          "E5oXBfjQ6I2hb4gwWt8nVWNoD00peCvFKe5Jj9esfws=": {
            "valueMac": {
              "type": "Buffer",
              "data": "QI0TbsS296vFY1v8/SsJlOdFWFUCi7gR5yc09V4xzbg="
            }
          },
          "dfU+67G8wpGtemFu3FeLZD+WWqkls27d5e7+qfQQyB8=": {
            "valueMac": {
              "type": "Buffer",
              "data": "LxPARvQhbVja6Jxpq9SyMapg8K42alAkqpCRuPQCYnw="
            }
          },
          "RarAoHj2+11Dt+Q326T7tJph8YwsPzNnHmucSFCQRyY=": {
            "valueMac": {
              "type": "Buffer",
              "data": "mMao8z2KYd8CxfiWEEAeWabFQ9VJg11dvZgFLBx9VXs="
            }
          },
          "PDc4WpDybahcx8sA0GNM8KjBMpqSXAm2mnYkOc4Z5Rs=": {
            "valueMac": {
              "type": "Buffer",
              "data": "BcqYv1g3qkAHHlRvGOMmi1rjv3XCYKiFOTNWz6QGPI4="
            }
          },
          "xmq8ZEFXPwAWrZSFWuj3rB47mvLrkRDsqqbQB1nvksM=": {
            "valueMac": {
              "type": "Buffer",
              "data": "6VS0LP8cb4P3WjF/tpdEtni/guGfOaqCvQ6fMrm3kxE="
            }
          },
          "u+72J1nQ2YYT5adze90JnMmHH37EXI3GqFftT/fjzkY=": {
            "valueMac": {
              "type": "Buffer",
              "data": "Wa8bw3adgX3kv1qGERW3yzY7rgaA9fyyEBfWu4mZkik="
            }
          },
          "RZVFD/4E+h3RyAZZAoWeGngP/K61CTuG6uSqRQ/GK2Y=": {
            "valueMac": {
              "type": "Buffer",
              "data": "VbNJj1gyxLHurZebpdVDPMBI3NJ5mlZ+dUDo5Qd4xY0="
            }
          },
          "HGfviv1UsZJC0pm2NRiBiFQNPAFEcPuts3EbdwanP90=": {
            "valueMac": {
              "type": "Buffer",
              "data": "UBfV8R4ZHfxn1SnK1jGqH076XPsvdjeFJYROZjiwFDg="
            }
          },
          "NqBgmhgBTEjbsussUk6ObuftIV1IKqPxpEhBBah9wY0=": {
            "valueMac": {
              "type": "Buffer",
              "data": "q3hJX9GzUNUBL5Rk5AEO13FsbZ4FoEYUtErNvM0h7dw="
            }
          },
          "GY5oWWk9YLC5KMevwmAByH/ENor5R/vRW2SV1SZ2DRE=": {
            "valueMac": {
              "type": "Buffer",
              "data": "D3E+y/EhaLsmcGJYbxPc6Gvwj7DSp5Mk9sS331bVcBQ="
            }
          }
        }
      },
      "regular_low": {
        "version": 1,
        "hash": {
          "type": "Buffer",
          "data": "6qUGujH3LleeDhZV6rzJ1cvCgasafd6w6hFhjw37l2Sx0VIjjnXo6qVXw/i/nGcnC3ElbkuJ7ehmc4hKQFFLZ3a5XYfrJejJywKEPX4A5NbbCPhzHtu6Mc9mBfFnGBP6YkFb9IdY0Dh2HGLR22XqCqRnZwo8SHg4GMN4FQPgpjg="
        },
        "indexValueMap": {
          "B51J5X5JYFqJgvzqeeAdXgrVUBrhHteczdsLno1+ieA=": {
            "valueMac": {
              "type": "Buffer",
              "data": "skMohv1fFpPSqVkGXb4pepTznw7llIM1UYqYsLsIvFA="
            }
          },
          "jwGfBQzUKZrPfY0l3fdmlkrXwEThi34JLiHKllFvoJg=": {
            "valueMac": {
              "type": "Buffer",
              "data": "njvZS6e+lev5LDN8huDKUcqWgoNdwM4Q36qgrU2Zt3s="
            }
          }
        }
      }
    }
  }
}